Color/Style.py
Color/__init__.py
MiColor-1.0.2.dist-info/LICENSE
MiColor-1.0.2.dist-info/METADATA
MiColor-1.0.2.dist-info/WHEEL
MiColor-1.0.2.dist-info/top_level.txt
MiColor-1.0.2.dist-info/RECORD
