Metadata-Version: 2.1
Name: MiColor
Version: 1.0.2
Summary: Manipulate console colours.
Home-page: https://github.com/milangcreations/Color
Author: MiLang Creations
Author-email: milangcreations@gmail.com
License: UNKNOWN
Project-URL: Bug Tracker, https://github.com/milangcreations/Color/issues
Platform: UNKNOWN
Classifier: Programming Language :: Python :: 3
Classifier: License :: OSI Approved :: MIT License
Classifier: Operating System :: OS Independent
Requires-Python: >=3.9
